HorribleDownloader/__init__.py
HorribleDownloader/cmd.py
HorribleDownloader/config_manager.py
HorribleDownloader/default_conf.ini
HorribleDownloader/parser.py
horrible_downloader-1.1.4.dist-info/LICENSE.txt
horrible_downloader-1.1.4.dist-info/METADATA
horrible_downloader-1.1.4.dist-info/WHEEL
horrible_downloader-1.1.4.dist-info/entry_points.txt
horrible_downloader-1.1.4.dist-info/top_level.txt
horrible_downloader-1.1.4.dist-info/RECORD
