Metadata-Version: 2.1
Name: horrible-downloader
Version: 1.1.4
Summary: HorribleSubs API
Home-page: https://github.com/mtshrmn/horrible-downloader
Author: Jelomite
Author-email: mtshrmn@gmail.com
License: MIT
Platform: UNKNOWN
Classifier: Programming Language :: Python :: 3.7
Classifier: License :: OSI Approved :: MIT License
Classifier: Operating System :: OS Independent
Requires-Dist: beautifulsoup4 (>=4)
Requires-Dist: requests (>=2)
Requires-Dist: lxml (>=4)
Requires-Dist: sty (>=1.0.0b9)
Requires-Dist: rapidfuzz (>=0.7.8)
